MANIFEST.in
README.rst
requirements.pip
setup.py
django_mxit.egg-info/PKG-INFO
django_mxit.egg-info/SOURCES.txt
django_mxit.egg-info/dependency_links.txt
django_mxit.egg-info/requires.txt
django_mxit.egg-info/top_level.txt
mxit/__init__.py
mxit/middleware.py